odoo/addons/product_active_propagate/README.rst
odoo/addons/product_active_propagate/__init__.py
odoo/addons/product_active_propagate/__manifest__.py
odoo/addons/product_active_propagate/i18n/fr.po
odoo/addons/product_active_propagate/i18n/it.po
odoo/addons/product_active_propagate/i18n/product_active_propagate.pot
odoo/addons/product_active_propagate/models/__init__.py
odoo/addons/product_active_propagate/models/product_product.py
odoo/addons/product_active_propagate/readme/CONTRIBUTORS.rst
odoo/addons/product_active_propagate/readme/DESCRIPTION.rst
odoo/addons/product_active_propagate/readme/DEVELOP.rst
odoo/addons/product_active_propagate/readme/INSTALL.rst
odoo/addons/product_active_propagate/static/description/icon.png
odoo/addons/product_active_propagate/static/description/index.html
odoo/addons/product_active_propagate/tests/__init__.py
odoo/addons/product_active_propagate/tests/test_module.py
odoo12_addon_product_active_propagate-12.0.1.0.1.99.dev6.dist-info/METADATA
odoo12_addon_product_active_propagate-12.0.1.0.1.99.dev6.dist-info/WHEEL
odoo12_addon_product_active_propagate-12.0.1.0.1.99.dev6.dist-info/top_level.txt
odoo12_addon_product_active_propagate-12.0.1.0.1.99.dev6.dist-info/RECORD
